sensospot_tools/__init__.py
sensospot_tools/hdr.py
sensospot_tools/helpers.py
sensospot_tools/selection.py
sensospot_tools-0.2.1.dist-info/LICENSE
sensospot_tools-0.2.1.dist-info/WHEEL
sensospot_tools-0.2.1.dist-info/METADATA
sensospot_tools-0.2.1.dist-info/RECORD
