Metadata-Version: 2.1
Name: sensospot_tools
Version: 0.2.1
Summary: Sensospot Tools
Author-email: Holger Frey <frey@imtek.de>
Requires-Python: >=3.9
Classifier: Development Status :: 2 - Pre-Alpha
Classifier: Intended Audience :: Developers
Classifier: Programming Language :: Python :: 3.8
Classifier: Programming Language :: Python :: 3.9
Classifier: Programming Language :: Python :: 3.10
Classifier: Programming Language :: Python :: 3 :: Only
Classifier: License :: Freely Distributable
Requires-Dist: pandas
Requires-Dist: black ; extra == "dev"
Requires-Dist: flit ; extra == "dev"
Requires-Dist: keyring ; extra == "dev"
Requires-Dist: pre-commit ; extra == "dev"
Requires-Dist: ruff ; extra == "dev"
Requires-Dist: mkdocs ; extra == "docs"
Requires-Dist: mkdocstrings[python] ; extra == "docs"
Requires-Dist: nox ; extra == "test"
Requires-Dist: pytest >=4.0.0 ; extra == "test"
Requires-Dist: pytest-cov ; extra == "test"
Requires-Dist: pytest-mock ; extra == "test"
Requires-Dist: pytest-randomly ; extra == "test"
Project-URL: Source, https://git.cpi.imtek.uni-freiburg.de/holgi/sensospot_tools.git
Provides-Extra: dev
Provides-Extra: docs
Provides-Extra: test
